vending_machine.v
`timescale 1ns/1ns
module vending_machine (
    input clock,
    input reset,
    input [1:0]in,
    output reg out,
    output reg[1:0]change);
    parameter s0 = 2'b00;
    parameter s1 = 2'b01;
    parameter s2 = 2'b10;
    reg[1:0] c_state,n_state;

    always @(posedge clock) 
    begin
      if (reset) 
      begin
        c_state = 0;
        n_state = 0;
        change = 2'b00;  
      end    
      else 
        c_state = n_state;

      case (c_state)
       s0 : if (in == 0) 
            begin
              n_state = s0;
              out = 0;
              change = 2'b00;
            end 
            else if(in == 2'b01)
            begin
               n_state = s1;
               out = 0;
               change = 2'b00;
            end
            else if(in == 2'b10)
            begin
                n_state = s2;
                out = 0;
                change = 2'b00;
            end
       s1 : if (in == 00) 
            begin
              n_state = s0;
              out = 0;
              change = 2'b01;
            end   
            else if(in == 2'b01)
            begin
               n_state = s2;
               out = 0;
               change = 2'b00; 
            end
            else if(in == 2'b10)
            begin
                n_state = s0;
                out = 1;
                change = 2'b00;
            end
       s2 : if (in == 0) 
            begin
               n_state = s0;
               out = 0;
               change = 2'b10;
            end   
            else if(in == 2'b01)
            begin
               n_state = s0;
               out = 1;
               change = 2'b00; 
            end 
            else if(in == 2'b10)
            begin
                n_state = s0;
                out = 1;
                change = 2'b01;
            end   
      endcase  
    end
endmodule

vending_machine_tb.v
`timescale 1ns/1ns
`include "vending_machine.v"
module vending_machine_tb;
   reg clock;
   reg reset;
   reg [1:0]in;

   wire out;
   wire [1:0]change;

   vending_machine vm(
    .clock(clock),
    .reset(reset),
    .in(in),
    .out(out),
    .change(change));

    initial 
    begin
      $dumpfile("vending_machine.vcd");
      $dumpvars(0,vending_machine_tb);
      clock = 0;
      forever #5 clock = ~clock;    
    end 

    initial 
    begin
      reset = 1;
      #10 reset = 0;
      in = 2'b01;
      #10 in = 2'b10;
      #10 in = 2'b01;
      #10 in = 2'b01;
      #10 in = 2'b10;
      #30 $finish;    
    end
endmodule

vending_machine.vcd
$date
	Tue Jul 16 20:56:33 2024
$end
$version
	Icarus Verilog
$end
$timescale
	1ns
$end
$scope module vending_machine_tb $end
$var wire 1 ! out $end
$var wire 2 " change [1:0] $end
$var reg 1 # clock $end
$var reg 2 $ in [1:0] $end
$var reg 1 % reset $end
$scope module vm $end
$var wire 1 # clock $end
$var wire 2 & in [1:0] $end
$var wire 1 % reset $end
$var reg 2 ' c_state [1:0] $end
$var reg 2 ( change [1:0] $end
$var reg 2 ) n_state [1:0] $end
$var reg 1 ! out $end
$upscope $end
$upscope $end
$enddefinitions $end
#0
$dumpvars
bx )
bx (
bx '
bx &
1%
bx $
0#
bx "
x!
$end
#5
b0 "
b0 (
b0 )
b0 '
1#
#10
0#
b1 $
b1 &
0%
#15
0!
b1 )
1#
#20
0#
b10 $
b10 &
#25
1!
b0 )
b1 '
1#
#30
0#
b1 $
b1 &
#35
0!
b1 )
b0 '
1#
#40
0#
#45
b10 )
b1 '
1#
#50
0#
b10 $
b10 &
#55
b1 "
b1 (
1!
b0 )
b10 '
1#
#60
0#
#65
b0 "
b0 (
0!
b10 )
b0 '
1#
#70
0#
#75
b1 "
b1 (
1!
b0 )
b10 '
1#
